docugenius/__init__.py
docugenius/cli/__init__.py
docugenius/cli/main.py
docugenius/common/__init__.py
docugenius/common/code_utils.py
docugenius/common/file_utils.py
docugenius/genius/__init__.py
docugenius/genius/genius.py
docugenius/genius/openai_genius.py
docugenius-0.1.3.dist-info/METADATA
docugenius-0.1.3.dist-info/WHEEL
docugenius-0.1.3.dist-info/entry_points.txt
docugenius-0.1.3.dist-info/top_level.txt
docugenius-0.1.3.dist-info/RECORD
