Metadata-Version: 2.1
Name: docugenius
Version: 0.1.3
Summary: Generate docustrings in seconds
Author: Samir Salman
Requires-Python: >=3.10
Requires-Dist: openai==1.55.2
Requires-Dist: mako==1.3.5
Provides-Extra: dev
Requires-Dist: mkdocs==1.6.1; extra == "dev"
Requires-Dist: mkdocs-material==9.5.48; extra == "dev"
Requires-Dist: mkdocstrings[python]; extra == "dev"
